stactools/viirs/__init__.py
stactools/viirs/cog.py
stactools/viirs/commands.py
stactools/viirs/constants.py
stactools/viirs/fragment.py
stactools/viirs/metadata.py
stactools/viirs/stac.py
stactools/viirs/utils.py
stactools/viirs/fragments/VNP09A1/collection.json
stactools/viirs/fragments/VNP09A1/item.json
stactools/viirs/fragments/VNP09H1/collection.json
stactools/viirs/fragments/VNP09H1/item.json
stactools/viirs/fragments/VNP10A1/collection.json
stactools/viirs/fragments/VNP10A1/item.json
stactools/viirs/fragments/VNP13A1/collection.json
stactools/viirs/fragments/VNP13A1/item.json
stactools/viirs/fragments/VNP14A1/collection.json
stactools/viirs/fragments/VNP14A1/item.json
stactools/viirs/fragments/VNP15A2H/collection.json
stactools/viirs/fragments/VNP15A2H/item.json
stactools/viirs/fragments/VNP21A2/collection.json
stactools/viirs/fragments/VNP21A2/item.json
stactools/viirs/fragments/VNP43IA4/collection.json
stactools/viirs/fragments/VNP43IA4/item.json
stactools/viirs/fragments/VNP43MA4/collection.json
stactools/viirs/fragments/VNP43MA4/item.json
stactools/viirs/fragments/VNP46A2/collection.json
stactools/viirs/fragments/VNP46A2/item.json
stactools_viirs-0.1.0.dist-info/LICENSE
stactools_viirs-0.1.0.dist-info/METADATA
stactools_viirs-0.1.0.dist-info/WHEEL
stactools_viirs-0.1.0.dist-info/top_level.txt
stactools_viirs-0.1.0.dist-info/RECORD
