Metadata-Version: 2.1
Name: stactools-viirs
Version: 0.1.0
Summary: stactools package for VIIRS sensor data
Home-page: https://github.com/stactools-packages/viirs
Author: Preston Hartzell
Author-email: preston.hartzell@gmail.com
Project-URL: Issues, https://github.com/stactools-packages/viirs/issues
Keywords: stactools,pystac,catalog,STAC
Classifier: Development Status :: 4 - Beta
Classifier: License :: OSI Approved :: Apache Software License
Classifier: Programming Language :: Python :: 3.7
Classifier: Programming Language :: Python :: 3.8
Classifier: Programming Language :: Python :: 3.9
License-File: LICENSE
Requires-Dist: stactools (>=0.3.1)
Requires-Dist: h5py (>=3.6.0)
Requires-Dist: click (!=8.1.0)
